grel_electricmeter/__init__.py
grel_electricmeter/_console.py
grel_electricmeter/config.py
grel_electricmeter/models.py
grel_electricmeter/reader.py
grel_electricmeter/sml.py
grel_electricmeter-0.1.1.dist-info/METADATA
grel_electricmeter-0.1.1.dist-info/WHEEL
grel_electricmeter-0.1.1.dist-info/entry_points.txt
grel_electricmeter-0.1.1.dist-info/RECORD
